gbsl_turtle/__init__.py
gbsl_turtle-0.0.13.dist-info/LICENSE
gbsl_turtle-0.0.13.dist-info/METADATA
gbsl_turtle-0.0.13.dist-info/WHEEL
gbsl_turtle-0.0.13.dist-info/top_level.txt
gbsl_turtle-0.0.13.dist-info/RECORD
